cxnstr.py
cxnstr-1.1.5.dist-info/LICENSE
cxnstr-1.1.5.dist-info/METADATA
cxnstr-1.1.5.dist-info/WHEEL
cxnstr-1.1.5.dist-info/entry_points.txt
cxnstr-1.1.5.dist-info/top_level.txt
cxnstr-1.1.5.dist-info/RECORD
