Metadata-Version: 2.1
Name: cxnstr
Version: 1.1.5
Summary: Parse database connection strings
Home-page: https://github.com/jobo3208/cxnstr
Author: Joe Boyd
Author-email: josefuboyd@gmail.com
License: UNKNOWN
Platform: UNKNOWN
Classifier: License :: OSI Approved :: MIT License
Classifier: Operating System :: OS Independent
Classifier: Programming Language :: Python :: 2
Classifier: Programming Language :: Python :: 3
Classifier: Topic :: Database
Requires-Dist: six (>=1.11.0)
